{"ID":3413829,"CITY":"Reykjavik","COUNTRY":"IS","SUNRISE":"21:01:58","SUNSET":"17:52:44","DAYLIGHT_HOURS":20.85,"TIMEZONE":0,"RANK":1}
{"ID":658225,"CITY":"Helsinki","COUNTRY":"FI","SUNRISE":"21:56:42","SUNSET":"16:43:19","DAYLIGHT_HOURS":18.78,"TIMEZONE":10800,"RANK":2}
{"ID":3143244,"CITY":"Oslo","COUNTRY":"NO","SUNRISE":"21:56:16","SUNSET":"16:37:16","DAYLIGHT_HOURS":18.68,"TIMEZONE":7200,"RANK":3}
{"ID":2673730,"CITY":"Stockholm","COUNTRY":"SE","SUNRISE":"21:33:08","SUNSET":"16:01:51","DAYLIGHT_HOURS":18.48,"TIMEZONE":7200,"RANK":4}
{"ID":524901,"CITY":"Moscow","COUNTRY":"RU","SUNRISE":"21:45:51","SUNSET":"15:12:43","DAYLIGHT_HOURS":17.45,"TIMEZONE":10800,"RANK":5}
{"ID":2618425,"CITY":"Copenhagen","COUNTRY":"DK","SUNRISE":"22:26:34","SUNSET":"15:52:25","DAYLIGHT_HOURS":17.43,"TIMEZONE":7200,"RANK":6}
{"ID":2964574,"CITY":"Dublin","COUNTRY":"IE","SUNRISE":"22:57:30","SUNSET":"15:52:10","DAYLIGHT_HOURS":16.91,"TIMEZONE":3600,"RANK":7}
{"ID":2950159,"CITY":"Berlin","COUNTRY":"DE","SUNRISE":"22:43:43","SUNSET":"15:28:31","DAYLIGHT_HOURS":16.75,"TIMEZONE":7200,"RANK":8}
{"ID":2759794,"CITY":"Amsterdam","COUNTRY":"NL","SUNRISE":"23:18:40","SUNSET":"16:01:44","DAYLIGHT_HOURS":16.72,"TIMEZONE":7200,"RANK":9}
{"ID":756135,"CITY":"Warsaw","COUNTRY":"PL","SUNRISE":"22:15:01","SUNSET":"14:56:23","DAYLIGHT_HOURS":16.69,"TIMEZONE":7200,"RANK":10}
