{"City_ID":98182,"Cloudiness_Percentage":17,"Wind_Direction_Degree":0,"Gust_Speed":null,"Wind_Speed":1.03}
{"City_ID":108410,"Cloudiness_Percentage":1,"Wind_Direction_Degree":300,"Gust_Speed":3.15,"Wind_Speed":2.67}
{"City_ID":112931,"Cloudiness_Percentage":20,"Wind_Direction_Degree":220,"Gust_Speed":null,"Wind_Speed":2.06}
{"City_ID":184745,"Cloudiness_Percentage":75,"Wind_Direction_Degree":200,"Gust_Speed":null,"Wind_Speed":2.57}
{"City_ID":264371,"Cloudiness_Percentage":20,"Wind_Direction_Degree":340,"Gust_Speed":null,"Wind_Speed":4.12}
{"City_ID":292223,"Cloudiness_Percentage":0,"Wind_Direction_Degree":70,"Gust_Speed":null,"Wind_Speed":2.57}
{"City_ID":293397,"Cloudiness_Percentage":75,"Wind_Direction_Degree":140,"Gust_Speed":null,"Wind_Speed":4.12}
{"City_ID":360630,"Cloudiness_Percentage":0,"Wind_Direction_Degree":330,"Gust_Speed":null,"Wind_Speed":2.06}
{"City_ID":524901,"Cloudiness_Percentage":36,"Wind_Direction_Degree":281,"Gust_Speed":3.53,"Wind_Speed":2.27}
{"City_ID":658225,"Cloudiness_Percentage":20,"Wind_Direction_Degree":190,"Gust_Speed":4.02,"Wind_Speed":3.13}
{"City_ID":745044,"Cloudiness_Percentage":0,"Wind_Direction_Degree":30,"Gust_Speed":null,"Wind_Speed":4.63}
{"City_ID":756135,"Cloudiness_Percentage":75,"Wind_Direction_Degree":240,"Gust_Speed":null,"Wind_Speed":3.6}
{"City_ID":1275339,"Cloudiness_Percentage":75,"Wind_Direction_Degree":310,"Gust_Speed":null,"Wind_Speed":3.6}
{"City_ID":1581130,"Cloudiness_Percentage":100,"Wind_Direction_Degree":340,"Gust_Speed":5.84,"Wind_Speed":4.21}
{"City_ID":1609350,"Cloudiness_Percentage":100,"Wind_Direction_Degree":276,"Gust_Speed":7.13,"Wind_Speed":3.45}
{"City_ID":1642911,"Cloudiness_Percentage":40,"Wind_Direction_Degree":120,"Gust_Speed":null,"Wind_Speed":2.57}
{"City_ID":1668341,"Cloudiness_Percentage":40,"Wind_Direction_Degree":120,"Gust_Speed":null,"Wind_Speed":7.72}
{"City_ID":1701668,"Cloudiness_Percentage":100,"Wind_Direction_Degree":0,"Gust_Speed":null,"Wind_Speed":1.03}
{"City_ID":1735161,"Cloudiness_Percentage":20,"Wind_Direction_Degree":170,"Gust_Speed":null,"Wind_Speed":3.09}
{"City_ID":1816670,"Cloudiness_Percentage":0,"Wind_Direction_Degree":201,"Gust_Speed":7.09,"Wind_Speed":5.44}
{"City_ID":1835848,"Cloudiness_Percentage":0,"Wind_Direction_Degree":270,"Gust_Speed":null,"Wind_Speed":5.14}
{"City_ID":1850147,"Cloudiness_Percentage":75,"Wind_Direction_Degree":20,"Gust_Speed":null,"Wind_Speed":3.09}
{"City_ID":1880252,"Cloudiness_Percentage":75,"Wind_Direction_Degree":170,"Gust_Speed":null,"Wind_Speed":4.63}
{"City_ID":2063523,"Cloudiness_Percentage":20,"Wind_Direction_Degree":360,"Gust_Speed":null,"Wind_Speed":3.09}
{"City_ID":2147714,"Cloudiness_Percentage":20,"Wind_Direction_Degree":260,"Gust_Speed":null,"Wind_Speed":7.2}
{"City_ID":2193733,"Cloudiness_Percentage":75,"Wind_Direction_Degree":310,"Gust_Speed":null,"Wind_Speed":9.26}
{"City_ID":2332459,"Cloudiness_Percentage":20,"Wind_Direction_Degree":230,"Gust_Speed":null,"Wind_Speed":2.06}
{"City_ID":2553604,"Cloudiness_Percentage":11,"Wind_Direction_Degree":353,"Gust_Speed":2.03,"Wind_Speed":1.33}
{"City_ID":2618425,"Cloudiness_Percentage":75,"Wind_Direction_Degree":290,"Gust_Speed":null,"Wind_Speed":4.63}
{"City_ID":2643743,"Cloudiness_Percentage":54,"Wind_Direction_Degree":119,"Gust_Speed":3.58,"Wind_Speed":1.34}
{"City_ID":2657896,"Cloudiness_Percentage":78,"Wind_Direction_Degree":0,"Gust_Speed":null,"Wind_Speed":0.51}
{"City_ID":2673730,"Cloudiness_Percentage":100,"Wind_Direction_Degree":160,"Gust_Speed":null,"Wind_Speed":1.54}
{"City_ID":2759794,"Cloudiness_Percentage":20,"Wind_Direction_Degree":0,"Gust_Speed":null,"Wind_Speed":0.51}
{"City_ID":2761369,"Cloudiness_Percentage":0,"Wind_Direction_Degree":270,"Gust_Speed":null,"Wind_Speed":3.09}
{"City_ID":2800866,"Cloudiness_Percentage":0,"Wind_Direction_Degree":80,"Gust_Speed":null,"Wind_Speed":1.54}
{"City_ID":2950159,"Cloudiness_Percentage":75,"Wind_Direction_Degree":275,"Gust_Speed":16.09,"Wind_Speed":8.05}
{"City_ID":2964574,"Cloudiness_Percentage":20,"Wind_Direction_Degree":0,"Gust_Speed":null,"Wind_Speed":1.03}
{"City_ID":2988507,"Cloudiness_Percentage":0,"Wind_Direction_Degree":60,"Gust_Speed":null,"Wind_Speed":1.54}
{"City_ID":3054643,"Cloudiness_Percentage":35,"Wind_Direction_Degree":311,"Gust_Speed":3.13,"Wind_Speed":1.79}
{"City_ID":3067696,"Cloudiness_Percentage":20,"Wind_Direction_Degree":290,"Gust_Speed":null,"Wind_Speed":5.14}
{"City_ID":3117735,"Cloudiness_Percentage":20,"Wind_Direction_Degree":360,"Gust_Speed":null,"Wind_Speed":3.6}
{"City_ID":3143244,"Cloudiness_Percentage":6,"Wind_Direction_Degree":316,"Gust_Speed":2.7,"Wind_Speed":1.37}
{"City_ID":3169070,"Cloudiness_Percentage":0,"Wind_Direction_Degree":40,"Gust_Speed":null,"Wind_Speed":1.54}
{"City_ID":3369157,"Cloudiness_Percentage":56,"Wind_Direction_Degree":205,"Gust_Speed":5.81,"Wind_Speed":2.68}
{"City_ID":3413829,"Cloudiness_Percentage":0,"Wind_Direction_Degree":70,"Gust_Speed":null,"Wind_Speed":3.6}
{"City_ID":3435910,"Cloudiness_Percentage":0,"Wind_Direction_Degree":120,"Gust_Speed":0.0,"Wind_Speed":4.92}
{"City_ID":3448433,"Cloudiness_Percentage":0,"Wind_Direction_Degree":149,"Gust_Speed":8.38,"Wind_Speed":3.24}
{"City_ID":3530597,"Cloudiness_Percentage":75,"Wind_Direction_Degree":250,"Gust_Speed":null,"Wind_Speed":6.17}
{"City_ID":3871336,"Cloudiness_Percentage":5,"Wind_Direction_Degree":97,"Gust_Speed":1.15,"Wind_Speed":0.8}
{"City_ID":3936456,"Cloudiness_Percentage":100,"Wind_Direction_Degree":150,"Gust_Speed":null,"Wind_Speed":4.12}
{"City_ID":4887398,"Cloudiness_Percentage":1,"Wind_Direction_Degree":238,"Gust_Speed":6.96,"Wind_Speed":2.65}
{"City_ID":5128581,"Cloudiness_Percentage":0,"Wind_Direction_Degree":190,"Gust_Speed":null,"Wind_Speed":2.06}
{"City_ID":5368361,"Cloudiness_Percentage":100,"Wind_Direction_Degree":230,"Gust_Speed":null,"Wind_Speed":5.14}
{"City_ID":5856195,"Cloudiness_Percentage":40,"Wind_Direction_Degree":60,"Gust_Speed":12.35,"Wind_Speed":7.2}
{"City_ID":6167865,"Cloudiness_Percentage":20,"Wind_Direction_Degree":240,"Gust_Speed":0.0,"Wind_Speed":5.81}
{"City_ID":6173331,"Cloudiness_Percentage":99,"Wind_Direction_Degree":235,"Gust_Speed":8.49,"Wind_Speed":4.92}
